malachite/__init__.py
malachite/__main__.py
malachite-2.0.12.dist-info/METADATA
malachite-2.0.12.dist-info/WHEEL
malachite-2.0.12.dist-info/entry_points.txt
malachite-2.0.12.dist-info/top_level.txt
malachite-2.0.12.dist-info/RECORD
