Metadata-Version: 2.1
Name: malachite
Version: 2.0.12
Summary: A Gene Enrichment Meta-Analysis (GEM) Tool for ToppGene
Home-page: https://github.com/ggersh/malachite-final
Author: Gregory R. Gershkowitz, Zachary B. Abrams, Kevin R. Coombes
Author-email: kevin.coombes@osumc.edu
License: UNKNOWN
Platform: UNKNOWN
Classifier: Programming Language :: Python :: 3
Classifier: License :: OSI Approved :: Apache Software License
Classifier: Operating System :: OS Independent
Requires-Dist: bs4
Requires-Dist: mechanize
Requires-Dist: requests
Requires-Dist: lxml
Requires-Dist: xlrd
